cross/__init__.py
cross/auto_transform.py
cross/cross_transformer.py
cross/auto_parameters/__init__.py
cross/auto_parameters/categorical_features/__init__.py
cross/auto_parameters/categorical_features/categorical_enconding.py
cross/auto_parameters/distribution_n_scale/__init__.py
cross/auto_parameters/distribution_n_scale/non_linear_transformation.py
cross/auto_parameters/distribution_n_scale/normalization.py
cross/auto_parameters/distribution_n_scale/quantile_transformation.py
cross/auto_parameters/distribution_n_scale/scale_transformation.py
cross/auto_parameters/features_reduction/__init__.py
cross/auto_parameters/features_reduction/column_selection.py
cross/auto_parameters/features_reduction/dimensionality_reduction.py
cross/auto_parameters/missing_n_outliers/__init__.py
cross/auto_parameters/missing_n_outliers/missing_values_handler.py
cross/auto_parameters/missing_n_outliers/missing_values_indicator.py
cross/auto_parameters/missing_n_outliers/outliers_handler.py
cross/auto_parameters/numerical_features/__init__.py
cross/auto_parameters/numerical_features/mathematical_operations.py
cross/auto_parameters/numerical_features/numerical_binning.py
cross/auto_parameters/numerical_features/spline_transformation.py
cross/auto_parameters/periodic_features/__init__.py
cross/auto_parameters/periodic_features/cyclical_features_transformer.py
cross/auto_parameters/periodic_features/datetime_transformer.py
cross/auto_parameters/shared/__init__.py
cross/auto_parameters/shared/evaluate_model/__init__.py
cross/auto_parameters/shared/evaluate_model/evaluate_model.py
cross/auto_parameters/shared/feature_selector/__init__.py
cross/auto_parameters/shared/feature_selector/probe_selector.py
cross/auto_parameters/shared/feature_selector/recursive_feature_addition.py
cross/auto_parameters/shared/feature_selector/shared/__init__.py
cross/auto_parameters/shared/feature_selector/shared/feature_importance.py
cross/auto_parameters/shared/utils/__init__.py
cross_ml-2.0.0.dist-info/METADATA
cross_ml-2.0.0.dist-info/WHEEL
cross_ml-2.0.0.dist-info/RECORD
