Metadata-Version: 2.4
Name: cross_ml
Version: 2.0.0
Summary: A comprehensive library for automatic feature engineering in machine learning
Author-email: Andres Di Giovanni <andresdigiovanni@gmail.com>
License-Expression: MIT
Keywords: automl,data preprocessing,data processing,feature engineering,machine learning,scikit-learn
Requires-Python: >=3.11
Requires-Dist: category-encoders>=2.6.3
Requires-Dist: matplotlib>=3.9.0
Requires-Dist: pandas>=2.2.2
Requires-Dist: scikit-learn>=1.5.0
Requires-Dist: tqdm>=4.66.5
